README.md
setup.py
anytarget/__init__.py
anytarget/country.py
anytarget.egg-info/PKG-INFO
anytarget.egg-info/SOURCES.txt
anytarget.egg-info/dependency_links.txt
anytarget.egg-info/entry_points.txt
anytarget.egg-info/requires.txt
anytarget.egg-info/top_level.txt