Metadata-Version: 2.1
Name: anytarget
Version: 0.1.0
Summary: This cli created to seamlessly interact with anytarget.net API
Author: Muhamed Qasim
Author-email: pyplus@protonmail.com
License: MIT
Project-URL: website, https://anytarget.net
Project-URL: source, https://github.com/caelghoul/anytarget
Keywords: anytarget
Classifier: Programming Language :: Python :: 3.10
Classifier: Intended Audience :: System Administrators
Classifier: Intended Audience :: Information Technology
Classifier: Topic :: Internet
Classifier: Topic :: Security
Classifier: Topic :: System :: Networking
Requires-Python: >=3.10
Requires-Dist: click>=8.1.7
Requires-Dist: httpx>=0.26.0
Requires-Dist: keyring>=24.3.0
Requires-Dist: tabulate>=0.9.0
Requires-Dist: tqdm>=4.66.1
